{
    "name": "root",
    "gauges": {
        "RollerBall.Policy.Entropy.mean": {
            "value": 1.4721355438232422,
            "min": 1.4721355438232422,
            "max": 1.4721355438232422,
            "count": 1
        },
        "RollerBall.Policy.Entropy.sum": {
            "value": 14725.771484375,
            "min": 14725.771484375,
            "max": 14725.771484375,
            "count": 1
        },
        "RollerBall.Environment.EpisodeLength.mean": {
            "value": 6.186063218390805,
            "min": 6.186063218390805,
            "max": 6.186063218390805,
            "count": 1
        },
        "RollerBall.Environment.EpisodeLength.sum": {
            "value": 8611.0,
            "min": 8611.0,
            "max": 8611.0,
            "count": 1
        },
        "RollerBall.Step.mean": {
            "value": 9997.0,
            "min": 9997.0,
            "max": 9997.0,
            "count": 1
        },
        "RollerBall.Step.sum": {
            "value": 9997.0,
            "min": 9997.0,
            "max": 9997.0,
            "count": 1
        },
        "RollerBall.Policy.ExtrinsicValueEstimate.mean": {
            "value": -4.665587425231934,
            "min": -4.665587425231934,
            "max": -4.665587425231934,
            "count": 1
        },
        "RollerBall.Policy.ExtrinsicValueEstimate.sum": {
            "value": -6489.83203125,
            "min": -6489.83203125,
            "max": -6489.83203125,
            "count": 1
        },
        "RollerBall.Policy.CuriosityValueEstimate.mean": {
            "value": 77.8848876953125,
            "min": 77.8848876953125,
            "max": 77.8848876953125,
            "count": 1
        },
        "RollerBall.Policy.CuriosityValueEstimate.sum": {
            "value": 108337.875,
            "min": 108337.875,
            "max": 108337.875,
            "count": 1
        },
        "RollerBall.Environment.CumulativeReward.mean": {
            "value": -9.67843264872697,
            "min": -9.67843264872697,
            "max": -9.67843264872697,
            "count": 1
        },
        "RollerBall.Environment.CumulativeReward.sum": {
            "value": -13462.699814379215,
            "min": -13462.699814379215,
            "max": -13462.699814379215,
            "count": 1
        },
        "RollerBall.Policy.ExtrinsicReward.mean": {
            "value": -4.839216324363485,
            "min": -4.839216324363485,
            "max": -4.839216324363485,
            "count": 1
        },
        "RollerBall.Policy.ExtrinsicReward.sum": {
            "value": -6731.349907189608,
            "min": -6731.349907189608,
            "max": -6731.349907189608,
            "count": 1
        },
        "RollerBall.Policy.CuriosityReward.mean": {
            "value": 2.4411870771436535,
            "min": 2.4411870771436535,
            "max": 2.4411870771436535,
            "count": 1
        },
        "RollerBall.Policy.CuriosityReward.sum": {
            "value": 3395.691224306822,
            "min": 3395.691224306822,
            "max": 3395.691224306822,
            "count": 1
        },
        "RollerBall.Losses.PolicyLoss.mean": {
            "value": 0.24388063224748915,
            "min": 0.24388063224748915,
            "max": 0.24388063224748915,
            "count": 1
        },
        "RollerBall.Losses.PolicyLoss.sum": {
            "value": 23.16866006351147,
            "min": 23.16866006351147,
            "max": 23.16866006351147,
            "count": 1
        },
        "RollerBall.Losses.ValueLoss.mean": {
            "value": 1.7357219745435417,
            "min": 1.7357219745435417,
            "max": 1.7357219745435417,
            "count": 1
        },
        "RollerBall.Losses.ValueLoss.sum": {
            "value": 164.89358758163647,
            "min": 164.89358758163647,
            "max": 164.89358758163647,
            "count": 1
        },
        "RollerBall.Policy.LearningRate.mean": {
            "value": 0.00029695635890928415,
            "min": 0.00029695635890928415,
            "max": 0.00029695635890928415,
            "count": 1
        },
        "RollerBall.Policy.LearningRate.sum": {
            "value": 0.028210854096381997,
            "min": 0.028210854096381997,
            "max": 0.028210854096381997,
            "count": 1
        },
        "RollerBall.Policy.Epsilon.mean": {
            "value": 0.19898545263157896,
            "min": 0.19898545263157896,
            "max": 0.19898545263157896,
            "count": 1
        },
        "RollerBall.Policy.Epsilon.sum": {
            "value": 18.903618,
            "min": 18.903618,
            "max": 18.903618,
            "count": 1
        },
        "RollerBall.Policy.Beta.mean": {
            "value": 0.0004950287178947369,
            "min": 0.0004950287178947369,
            "max": 0.0004950287178947369,
            "count": 1
        },
        "RollerBall.Policy.Beta.sum": {
            "value": 0.04702772820000001,
            "min": 0.04702772820000001,
            "max": 0.04702772820000001,
            "count": 1
        },
        "RollerBall.Losses.CuriosityForwardLoss.mean": {
            "value": 5.1156419164340035,
            "min": 5.1156419164340035,
            "max": 5.1156419164340035,
            "count": 1
        },
        "RollerBall.Losses.CuriosityForwardLoss.sum": {
            "value": 485.98598206123035,
            "min": 485.98598206123035,
            "max": 485.98598206123035,
            "count": 1
        },
        "RollerBall.Losses.CuriosityInverseLoss.mean": {
            "value": 1.3802838046264332,
            "min": 1.3802838046264332,
            "max": 1.3802838046264332,
            "count": 1
        },
        "RollerBall.Losses.CuriosityInverseLoss.sum": {
            "value": 131.12696143951115,
            "min": 131.12696143951115,
            "max": 131.12696143951115,
            "count": 1
        },
        "RollerBall.IsTraining.mean": {
            "value": 1.0,
            "min": 1.0,
            "max": 1.0,
            "count": 1
        },
        "RollerBall.IsTraining.sum": {
            "value": 1.0,
            "min": 1.0,
            "max": 1.0,
            "count": 1
        }
    },
    "metadata": {
        "timer_format_version": "0.1.0",
        "start_time_seconds": "1642850074",
        "python_version": "3.7.8 (tags/v3.7.8:4b47a5b6ba, Jun 28 2020, 08:53:46) [MSC v.1916 64 bit (AMD64)]",
        "command_line_arguments": "C:\\Users\\ocuat\\AppData\\Roaming\\Python\\Python37\\Scripts\\mlagents-learn config/rollerball_config.yaml --run-id=RollerBall --force",
        "mlagents_version": "0.27.0",
        "mlagents_envs_version": "0.27.0",
        "communication_protocol_version": "1.5.0",
        "pytorch_version": "1.10.1+cu113",
        "numpy_version": "1.21.5",
        "end_time_seconds": "1642850335"
    },
    "total": 261.631209,
    "count": 1,
    "self": 0.004743900000050871,
    "children": {
        "run_training.setup": {
            "total": 0.05754720000000002,
            "count": 1,
            "self": 0.05754720000000002
        },
        "TrainerController.start_learning": {
            "total": 261.5689179,
            "count": 1,
            "self": 0.3010192000004963,
            "children": {
                "TrainerController._reset_env": {
                    "total": 15.8874535,
                    "count": 1,
                    "self": 15.8874535
                },
                "TrainerController.advance": {
                    "total": 245.25184689999952,
                    "count": 20820,
                    "self": 0.2929096000017921,
                    "children": {
                        "env_step": {
                            "total": 172.73145199999826,
                            "count": 20820,
                            "self": 125.64378849999578,
                            "children": {
                                "SubprocessEnvManager._take_step": {
                                    "total": 46.90306230000152,
                                    "count": 20820,
                                    "self": 0.7176049999999705,
                                    "children": {
                                        "TorchPolicy.evaluate": {
                                            "total": 46.18545730000155,
                                            "count": 18141,
                                            "self": 21.78652620000032,
                                            "children": {
                                                "TorchPolicy.sample_actions": {
                                                    "total": 24.39893110000123,
                                                    "count": 18141,
                                                    "self": 24.39893110000123
                                                }
                                            }
                                        }
                                    }
                                },
                                "workers": {
                                    "total": 0.18460120000095515,
                                    "count": 20819,
                                    "self": 0.0,
                                    "children": {
                                        "worker_root": {
                                            "total": 246.16628840000007,
                                            "count": 20819,
                                            "is_parallel": true,
                                            "self": 132.8830789000017,
                                            "children": {
                                                "steps_from_proto": {
                                                    "total": 0.00032389999999971053,
                                                    "count": 1,
                                                    "is_parallel": true,
                                                    "self": 0.00016530000000081202,
                                                    "children": {
                                                        "_process_rank_one_or_two_observation": {
                                                            "total": 0.0001585999999988985,
                                                            "count": 2,
                                                            "is_parallel": true,
                                                            "self": 0.0001585999999988985
                                                        }
                                                    }
                                                },
                                                "UnityEnvironment.step": {
                                                    "total": 113.28288559999838,
                                                    "count": 20819,
                                                    "is_parallel": true,
                                                    "self": 1.181937299997685,
                                                    "children": {
                                                        "UnityEnvironment._generate_step_input": {
                                                            "total": 0.8528245000002954,
                                                            "count": 20819,
                                                            "is_parallel": true,
                                                            "self": 0.8528245000002954
                                                        },
                                                        "communicator.exchange": {
                                                            "total": 107.50086470000106,
                                                            "count": 20819,
                                                            "is_parallel": true,
                                                            "self": 107.50086470000106
                                                        },
                                                        "steps_from_proto": {
                                                            "total": 3.74725909999934,
                                                            "count": 20819,
                                                            "is_parallel": true,
                                                            "self": 2.3181935999965653,
                                                            "children": {
                                                                "_process_rank_one_or_two_observation": {
                                                                    "total": 1.4290655000027748,
                                                                    "count": 41638,
                                                                    "is_parallel": true,
                                                                    "self": 1.4290655000027748
                                                                }
                                                            }
                                                        }
                                                    }
                                                }
                                            }
                                        }
                                    }
                                }
                            }
                        },
                        "trainer_advance": {
                            "total": 72.22748529999947,
                            "count": 20819,
                            "self": 0.3709571999986707,
                            "children": {
                                "process_trajectory": {
                                    "total": 9.394108300000834,
                                    "count": 20819,
                                    "self": 9.394108300000834
                                },
                                "_update_policy": {
                                    "total": 62.46241979999997,
                                    "count": 175,
                                    "self": 2.1877837999998277,
                                    "children": {
                                        "TorchPPOOptimizer.update": {
                                            "total": 60.27463600000014,
                                            "count": 5283,
                                            "self": 60.27463600000014
                                        }
                                    }
                                }
                            }
                        }
                    }
                },
                "trainer_threads": {
                    "total": 8.000000093488779e-07,
                    "count": 1,
                    "self": 8.000000093488779e-07
                },
                "TrainerController._save_models": {
                    "total": 0.1285974999999553,
                    "count": 1,
                    "self": 0.006503899999927398,
                    "children": {
                        "RLTrainer._checkpoint": {
                            "total": 0.12209360000002789,
                            "count": 1,
                            "self": 0.12209360000002789
                        }
                    }
                }
            }
        }
    }
}